Metadata-Version: 2.4
Name: mseep-mcp-server-any-openapi
Version: 0.1.4
Summary: MCP server for Any OpenAPI resources
Author-email: mseep <support@skydeck.ai>
License-File: LICENSE
Requires-Python: >=3.10
Requires-Dist: faiss-cpu
Requires-Dist: fastapi
Requires-Dist: huggingface-hub
Requires-Dist: mcp
Requires-Dist: numpy
Requires-Dist: pydantic
Requires-Dist: pytz
Requires-Dist: pyyaml
Requires-Dist: requests
Requires-Dist: sentence-transformers
Requires-Dist: uvicorn
